tldry/__init__.py
tldry/nlp.py
tldry/pdist_maker.py
tldry/tldry.py
tldry/stopwords/__init__.py
tldry/stopwords/english.py
tldry/stopwords/russian.py
tldry-0.3.4.dist-info/METADATA
tldry-0.3.4.dist-info/RECORD
tldry-0.3.4.dist-info/WHEEL
tldry-0.3.4.dist-info/top_level.txt
