Metadata-Version: 2.1
Name: tldry
Version: 0.3.4
Summary: Automatic text summarizer based on textrank algorithm
Home-page: https://github.com/vangaa/tldry
Author: Artem Vang
Author-email: vangogius@gmail.com
License: MIT License
Platform: UNKNOWN
Classifier: Programming Language :: Python
Classifier: Intended Audience :: Developers
Classifier: Programming Language :: Python :: 3.6
Classifier: Topic :: Software Development :: Libraries :: Python Modules
Classifier: Programming Language :: Python :: Implementation :: CPython
Requires-Dist: numpy
Requires-Dist: regex
Requires-Dist: PyStemmer (==1.3.0)
